{"sentiment": 55.7, "featured": [{"username": "jjhall18", "tweet": "President Trump won\ud83c\uddfa\ud83c\uddf8\ud83d\udcaf"}, {"username": "its_a_birdy", "tweet": "Trump won!"}, {"username": "ahernkeefe", "tweet": "Trump will Triumph!"}, {"username": "missybenson14", "tweet": "Pres.Trump\ud83d\udc7a\ud83d\udc7a\ud83d\udc7a"}, {"username": "liesaquinn", "tweet": "I LOVE PRESIDENT TRUMP"}, {"username": "photokp", "tweet": "Donald Trump is a proven liar."}, {"username": "brucehallsports", "tweet": "Trump won Arizona EASILY!"}, {"username": "loretta09822264", "tweet": "Trump,  God be with you"}, {"username": "jackruger1", "tweet": "Trump won!"}, {"username": "tonyflanaganuk", "tweet": "Donald Trump won!"}, {"username": "kufikiakwanyota", "tweet": "This is what Trump created."}, {"username": "patroit17762021", "tweet": "DONALD J. TRUMP WON"}, {"username": "slingdrinks", "tweet": "Trump 2020 Don Jr. 2024"}, {"username": "maddrenh", "tweet": "Trump is a murderer!!"}, {"username": "sotiredofthis11", "tweet": "THIS is the trump legacy!!!"}, {"username": "jashuaparez", "tweet": "Trump wins GA!!-"}, {"username": "luizaug72506741", "tweet": "Veto!!! Go Trump go"}, {"username": "doak_carrie", "tweet": "#TRUMP"}, {"username": "pureideologybot", "tweet": "Metaxist Donald Trump"}, {"username": "tamihigginboth1", "tweet": "Trump is my President"}, {"username": "susanissicofgop", "tweet": "They all know trump won"}, {"username": "ljustmabel", "tweet": "WE LOVE YOU PRESIDENT TRUMP!"}, {"username": "gail47467661", "tweet": "Trump 2020! Stop The Steal!"}, {"username": "doctorcherokee", "tweet": "Senile Joe Biden's showercam!"}, {"username": "fredmorin454", "tweet": "."}, {"username": "fred_mcghee", "tweet": "What will Biden do?"}, {"username": "ankleztwisted", "tweet": "Perdue: BIDEN WON AGAIN"}, {"username": "leanne53585521", "tweet": "Biden Cheated"}, {"username": "ohlookitsrafa", "tweet": "Knew this mf voted for biden"}, {"username": "amadan45", "tweet": "Patriot."}, {"username": "biden_my_time", "tweet": "Fucking moron"}, {"username": "natand511", "tweet": "Hum...I want bubbles...lol"}, {"username": "sadsiren_", "tweet": "HELP"}, {"username": "doak_carrie", "tweet": "#BYE BIDEN!!!"}, {"username": "pambb7", "tweet": "#PerdueSaysBidenWon pass it on"}, {"username": "amyoscorpio", "tweet": "BIDEN WON!  #TrumpIsPathetic"}, {"username": "biden_my_time", "tweet": "Slow as fuck Uber"}, {"username": "fredmorin454", "tweet": "Declare war on China!"}, {"username": "mjrossano", "tweet": "YIKES"}]}