{"sentiment": 51.1, "featured": [{"username": "huongkts", "tweet": "True!!!! Trump 2020!"}, {"username": "vanessa75998849", "tweet": "Trump has gone mad!"}, {"username": "don76331856", "tweet": "Trumps America"}, {"username": "shirley32003065", "tweet": "Trumps star witness lol"}, {"username": "albug56", "tweet": "Hiden Biden wants him"}, {"username": "unauthorizedbe1", "tweet": "Me too. I'm out. 'night."}, {"username": "blutexgal", "tweet": "\ud83c\udf7f\ud83c\udf7f\ud83c\udf7f"}, {"username": "steffiehome", "tweet": "#GOPDeathCult"}, {"username": "my_bordercollie", "tweet": "\ud83d\ude02\ud83d\ude02\ud83d\ude02\ud83d\ude02\ud83d\ude05\ud83d\ude05\ud83d\ude05\ud83d\ude05"}, {"username": "bigkingp", "tweet": "Yes lawddd"}, {"username": "bigkingp", "tweet": "\ud83d\ude02\ud83d\ude2d\ud83d\ude2d\ud83d\ude2d"}]}