{"sentiment": 53.4, "featured": [{"username": "stano0098", "tweet": "Donald Trump Won."}, {"username": "desus_bot", "tweet": "Trump gonna"}, {"username": "bethh_persist", "tweet": "THIS is trump now!"}, {"username": "cheneychihuahua", "tweet": "TRUMP IS MY PRESIDENT \ud83c\uddfa\ud83c\uddf8"}, {"username": "charcrnll", "tweet": "Donald Trump is despicable."}, {"username": "elhziq", "tweet": "Oomf is a trump supporter"}, {"username": "swissjldd", "tweet": "\ud83e\udd25"}, {"username": "wisemanbill", "tweet": "Biden won Georgia"}, {"username": "floppyjoebiden", "tweet": "Toxic Masculinity!"}, {"username": "ltsrowe", "tweet": "The tail wags the dog.  #Biden"}, {"username": "columbus_todd", "tweet": "#PerdueSaysBidenWon"}, {"username": "sourgra32364954", "tweet": "Sleepy FAKER Biden."}]}