{"sentiment": 52.5, "featured": [{"username": "zelamagaly", "tweet": "Trump 2020! \ud83c\uddfa\ud83c\uddf8\ud83c\uddfa\ud83c\uddf8\ud83c\uddfa\ud83c\uddf8"}, {"username": "hansen_jair", "tweet": "Go Trump. Stop the Fraud!"}, {"username": "lili_mii", "tweet": "\ud83c\uddfa\ud83c\uddf8\ud83c\uddfa\ud83c\uddf8\ud83c\uddfa\ud83c\uddf8GOGO Trump\ud83c\uddfa\ud83c\uddf8\ud83c\uddfa\ud83c\uddf8\ud83c\uddfa\ud83c\uddf8 #MAGA"}, {"username": "sheliapulley", "tweet": "Trump will WIN!"}, {"username": "truzenuzex", "tweet": "Market happy trump is leaving"}]}