{"sentiment": 68.8, "featured": [{"username": "crocks69", "tweet": "KEEP IT GOING TRUMP!!!!!!"}, {"username": "misspete64", "tweet": "Trump won.. #AmericaLovesTrump"}, {"username": "trumptajmawall", "tweet": "Trump Won Georgia"}, {"username": "mistydgrantham", "tweet": "Thank you President Trump"}, {"username": "johan4cardenas", "tweet": "Vamos t\u00edo Trump\ud83d\udc4f\ud83c\udffd"}, {"username": "mike73031421", "tweet": "Trump will be Re-elected!"}, {"username": "mariafl38850356", "tweet": "Go Trump"}, {"username": "f1harris", "tweet": "Same as trump then ?"}, {"username": "markdav757", "tweet": "Hear comes the Trump train!"}, {"username": "debradaingerfi1", "tweet": "Trump is so desparate"}, {"username": "darkqueen821", "tweet": "Well so is trump so...."}, {"username": "zhongjiehuang2", "tweet": "Did Trump lose\uff1f Maybe NOT"}, {"username": "julialove", "tweet": "And Trump nightmares."}, {"username": "ijuanjosearcila", "tweet": "see how stupid trump sounds?"}, {"username": "carolyncatt", "tweet": "TRUMP\u2019S COGNITIVE TEST..."}, {"username": "allisontappan5", "tweet": "Trump has his reasons"}, {"username": "richjaeger", "tweet": "\u2705 GEORGIA GOES TO TRUMP"}, {"username": "craz4e", "tweet": "Biden should sue Trump"}, {"username": "inlawsattic", "tweet": "MAGA ! YEA TRUMP!"}, {"username": "mmyers2020maga", "tweet": "Trump won 44%???"}, {"username": "mradant68", "tweet": "Where\u2019s the homie trump?"}, {"username": "danielchiroque", "tweet": "Trump"}, {"username": "calbro84", "tweet": "#Trump"}, {"username": "king__dreadhead", "tweet": "Ppl tht support trump"}, {"username": "babetruth2", "tweet": "Trump is insane."}, {"username": "lilinaescarra", "tweet": "Trump 2020"}, {"username": "judyowe59486457", "tweet": "She\u2019s a trump mouthpiece"}, {"username": "livorleave", "tweet": "a trump voter \u2764\ufe0f"}, {"username": "pattiboland3", "tweet": "I found Trumps library \ud83d\udcda"}, {"username": "_onlykeyla", "tweet": "Y\u2019all where is Trump?"}, {"username": "alician37553537", "tweet": "They are Trump zombies"}, {"username": "hrh_nanaanane", "tweet": "Trump cultist won't read this"}, {"username": "kriptamydear", "tweet": "Y gracias al apoyo de TRUMP"}, {"username": "beautifully_kj", "tweet": "Y\u2019all better call Daddy Trump"}, {"username": "zreally450", "tweet": "Trumps payoff"}, {"username": "bodhichae", "tweet": "^^if i was a trump supporter"}, {"username": "richardson9mike", "tweet": "I'm sure Trump will win"}, {"username": "cat_biden", "tweet": "#Icon #Trending #BreakingNews"}, {"username": "f33t0nth3str33t", "tweet": "I'll take 4"}, {"username": "chucktownbabe", "tweet": "i got tears in my eyes \ud83d\ude2d\ud83d\ude2d\ud83d\ude2d\ud83d\ude2d"}, {"username": "islandgirl_024", "tweet": "Following \ud83c\udf3a"}, {"username": "homemrinite", "tweet": "o carro de som matou a fazenda"}, {"username": "michell59850493", "tweet": "Biden is NOT MY PRESIDENT"}, {"username": "aflaguemona", "tweet": "I voted for Biden. Pass it on."}, {"username": "sonyawh55919237", "tweet": "Biden you seeing this?"}, {"username": "mj07810", "tweet": "THIS!"}, {"username": "ch_niya_", "tweet": "Shrek 2 \ud83e\udd23"}, {"username": "merrittwife", "tweet": "Joe Biden is my president."}, {"username": "iskolarbonez", "tweet": "Ew pick a struggle teh"}, {"username": "bestiaytiesa", "tweet": "Ten points to griffyntrump"}, {"username": "randyfewell", "tweet": "#RetireRubio"}, {"username": "gmonsterthegoon", "tweet": "did joe biden win the erection"}, {"username": "sica4byu", "tweet": "Heartbreaking"}, {"username": "herveeisa", "tweet": "Go to Jail Joe Biden!"}, {"username": "ojosand", "tweet": "\ud83e\udd23\ud83e\udd23\ud83e\udd23\ud83e\udd23\ud83e\udd23#Biden"}, {"username": "timoth5141", "tweet": "Joe Biden is not verified."}, {"username": "micaellalala", "tweet": "Idk this shit hit different"}, {"username": "tnmouth", "tweet": "Good. Another state for Biden"}, {"username": "chatbrat11", "tweet": "They knew better!"}, {"username": "hellocldwrld", "tweet": "I love him so fucking much"}, {"username": "elizabe86662794", "tweet": "They are despicable"}, {"username": "cristodeelqui", "tweet": "Adhiero!"}, {"username": "sylviad45103002", "tweet": "Shes a nit"}, {"username": "itslindshere", "tweet": "hello Biden, bye don!"}, {"username": "sircoochieman", "tweet": "I like to touch on little kids"}, {"username": "fixation_30", "tweet": "Biden out to $1.10"}, {"username": "shallowdeep", "tweet": "How are y'all staying calm?"}, {"username": "richard09157242", "tweet": "biden is great"}, {"username": "foxwallace1", "tweet": "\u2665\ufe0f\ud83d\udc4f\u2665\ufe0f\ud83d\udc4f\u2665\ufe0f"}, {"username": "elizabe86662794", "tweet": "Exactly"}, {"username": "samkoi", "tweet": "way to go, Biden-Harris! \ud83c\uddfa\ud83c\uddf8"}, {"username": "ashley1thegreat", "tweet": "U can make me do shit biden"}, {"username": "mattmackowiak", "tweet": "Biden can ask Buzzfeed for it"}, {"username": "craz4e", "tweet": "Biden should sue Trump"}, {"username": "leoht60", "tweet": "OMG FUCKING HILARIOUS"}, {"username": "luvbidenharris", "tweet": "Pack your shit."}, {"username": "kharlokong", "tweet": "This game is PHENOMENAL"}, {"username": "quijotemagnus", "tweet": "BIDEN FOR PRISON 2020 !!"}, {"username": "misterquavo", "tweet": "Biden won.. get over it \ud83d\ude02"}, {"username": "fernanda_seabra", "tweet": "Toma essa outra #biden ! \ud83d\ude02\ud83d\ude02\ud83d\ude02\ud83d\ude02\ud83d\ude02"}, {"username": "thatruth12345", "tweet": "Damn !!!!!!!"}, {"username": "tkobeauty", "tweet": "Spot on!"}, {"username": "jagsmac", "tweet": "Yep. Biden won there too."}, {"username": "garbii93", "tweet": "God\u2026"}, {"username": "newt50", "tweet": "YES PLEASE!!!"}, {"username": "elizabe86662794", "tweet": "Very true and so disgusting."}, {"username": "taewlts", "tweet": "gm bachon"}, {"username": "iousstas", "tweet": "hopefully biden burns trees"}, {"username": "stereo_fred", "tweet": "Biden is not President elect \ud83e\udd14"}, {"username": "nenaadelmann", "tweet": "One more time"}, {"username": "foxwallace1", "tweet": "\ud83d\udc95\ud83d\udc95\ud83d\udc95\ud83d\udc95\ud83d\udc95"}, {"username": "sighandy58_andy", "tweet": "BIDEN THE UNIFIER"}, {"username": "ish_not", "tweet": "Damn.  Facts."}, {"username": "sagi_o_taria", "tweet": "Gente ela \u00e9 100% Biden"}, {"username": "agenthxrgreeves", "tweet": "tess harding"}, {"username": "r_lizmi", "tweet": "Biden crap belonging to CCP"}, {"username": "foxwallace1", "tweet": "\ud83c\udf08\ud83c\udff3\ufe0f\u200d\ud83c\udf08\ud83c\udf08\ud83c\udff3\ufe0f\u200d\ud83c\udf08\ud83c\udf08\ud83c\udff3\ufe0f\u200d\ud83c\udf08"}, {"username": "ukexpat19", "tweet": "INSIDER TRADER!"}, {"username": "ferraznilo", "tweet": "Sobre o biden"}, {"username": "leoht60", "tweet": "THEY. TOOK. NO. FUNDING."}, {"username": "z9bill", "tweet": "This is an excellent article."}, {"username": "gideonadu20", "tweet": "I liked Joe Biden\u2019s speech."}, {"username": "fernanda_seabra", "tweet": "Toma #biden ! \ud83d\ude02\ud83d\ude02\ud83d\ude02\ud83d\ude02"}, {"username": "kc_martin12", "tweet": "#LockThemUp"}, {"username": "agenthxrgreeves", "tweet": "raven"}, {"username": "jdnewengland", "tweet": "FFS \ud83e\udd26\u200d\u2640\ufe0f"}, {"username": "sharkinfishbowl", "tweet": "Pennsylvania pulled from Biden"}, {"username": "foxwallace1", "tweet": "\u2665\ufe0f\u2665\ufe0f\u2665\ufe0f\u2665\ufe0f\u2665\ufe0f"}, {"username": "heavensworld__", "tweet": "So biden didn\u2019t win?"}, {"username": "leoht60", "tweet": "You are a pissant of lies"}, {"username": "lourdes93195410", "tweet": "Thank you Mr President Biden"}, {"username": "tkobeauty", "tweet": "Moar?!"}, {"username": "nenaadelmann", "tweet": "\ud83d\ude32\ud83d\ude32\ud83d\ude21"}, {"username": "therealbisneck", "tweet": "Amen\ud83d\ude4f\ud83c\udffd"}, {"username": "pacheightsmom", "tweet": "Hunter Biden owns this hole"}, {"username": "spencerw", "tweet": "Who will Biden bomb? #WWBB"}, {"username": "calif0rnio", "tweet": "yuuup"}, {"username": "smoovedeeeezy", "tweet": "Biden lost Pennsylvania \ud83d\udc40"}, {"username": "fotcangela", "tweet": "Beautiful!"}, {"username": "nenaadelmann", "tweet": "#LIARS"}, {"username": "writingman26", "tweet": "#Biden #COVID\u30fc19"}, {"username": "blutexgal", "tweet": "Amen\u203c\ufe0f"}, {"username": "bidenwin2020", "tweet": "#JoeIsMyPresident"}, {"username": "leoht60", "tweet": "Go Rob"}, {"username": "illictaffa1rs", "tweet": "gnite \ud83e\udd29\ud83e\udd29"}, {"username": "freewimin", "tweet": "\ud83d\udc47\ud83c\udffd"}, {"username": "laurabiden", "tweet": "Close you Twitter account!"}, {"username": "suzyq3131", "tweet": "Biden-always a class act."}, {"username": "luvwinsresist", "tweet": "Eat Skai Eat!!!! #DWTS"}, {"username": "jenesihaiti1", "tweet": "Great \ud83d\udc4d. Biden, Biden, Biden"}, {"username": "dardar458", "tweet": "#TrumpConcede"}, {"username": "francis71916455", "tweet": "me digam que Biden perdeu!"}, {"username": "prosecuteccp20", "tweet": "\u201c\u77a7\uff0c\u767d\u7b49\u201d\u662fJoe Biden\u6700\u4f20\u795e\u7684\u7ffb\u8bd1\u3002"}, {"username": "delventotime", "tweet": "Also ... \ud83d\udc40"}, {"username": "treygee254", "tweet": "Come through Ross!"}, {"username": "javierc24988318", "tweet": "Biden,corrupto y ped\u00f3filo."}]}