{"sentiment": 55.5, "featured": [{"username": "americanmom6", "tweet": "Trump won by a landslide!"}, {"username": "squirrel_ma", "tweet": "Trump and his lackeys"}, {"username": "richard_crouse", "tweet": "TRUMP 2Q2Q WWG1WGA."}, {"username": "4mrrmcdo", "tweet": "Trumps bagman?"}, {"username": "trebor00100", "tweet": "Thank you President Trump."}, {"username": "sabaisty", "tweet": "Au ah trump, ga ikutan oe."}, {"username": "julian20anthony", "tweet": "Donald Trump is a traitor"}, {"username": "joanmacinnis", "tweet": "Stop covering Trump"}, {"username": "harlem", "tweet": "Go Team Trump!!!!"}, {"username": "ezdan17", "tweet": "Biden should concede \ud83d\udcaa\ud83c\uddfa\ud83c\uddf8\ud83d\udc4d"}, {"username": "bidenisbest", "tweet": "Screw Israel, free Palestine"}, {"username": "ezdan17", "tweet": "Biden should concede \ud83d\udcaa\ud83c\uddfa\ud83c\uddf8\ud83d\udc4d"}, {"username": "texomachief", "tweet": "Not for Biden I\u2019m sure"}, {"username": "therealwil16", "tweet": "It\u2019s tradition \ud83d\ude0c"}, {"username": "ezdan17", "tweet": "Biden should concede \ud83d\udcaa\ud83c\uddfa\ud83c\uddf8\ud83d\udc4d"}, {"username": "hoefor_harry", "tweet": "JOE BIDEN"}, {"username": "ausanka", "tweet": "Solid move from Biden."}, {"username": "bidenisbernie", "tweet": "Suppressed truth\ud83d\udc47\ud83d\udc47\ud83d\udc47"}, {"username": "wandarbts", "tweet": "Low ratings!"}, {"username": "hotmessobsessed", "tweet": "SPEAK it Terrance \ud83d\udc4f\ud83c\udffb\ud83d\udc4f\ud83c\udffb\ud83d\udc4f\ud83c\udffb"}, {"username": "0niyangei_", "tweet": "biden"}, {"username": "julka_369", "tweet": "No way Biden..."}, {"username": "ezdan17", "tweet": "Biden should concede \ud83d\udcaa\ud83c\uddfa\ud83c\uddf8\ud83d\udc4d"}, {"username": "flnina4", "tweet": "Biden won!"}, {"username": "jd7286", "tweet": "Absolutely not!"}, {"username": "oldfatbat61", "tweet": "Wait untii is l Biden is in"}, {"username": "john41364102", "tweet": "Biden didn\u2019t win Jack!!!"}, {"username": "bidensgodson", "tweet": "ok"}]}