{"sentiment": 61.0, "featured": [{"username": "btsy7", "tweet": "bet trump will pardon him."}, {"username": "joyceejohnson5", "tweet": "Trump keeps on losing."}, {"username": "calbro84", "tweet": "#Trump #COVID\u30fc19 #Election2020"}, {"username": "feinsteinfan", "tweet": "Trump lost.."}, {"username": "shawn76367523", "tweet": "trump"}, {"username": "percetion", "tweet": "Trump Virus"}, {"username": "whowonthepv", "tweet": "Idk not Trump tho."}, {"username": "alllitupforyou", "tweet": "Hahaha \ud83d\ude02\ud83d\ude02\ud83d\ude02 Trump CULT members!"}, {"username": "9jkqcwgm9xdye7e", "tweet": "Only for Trump\u2019s republicans ."}, {"username": "zgongiveittoya", "tweet": "He really murked Trump \ud83e\udd74\ud83d\ude2d"}, {"username": "realhahnsolo", "tweet": "Trump is a loser"}, {"username": "roxceroller", "tweet": "Donald Trump won !!!!"}, {"username": "animemoto", "tweet": "Trump is screwed."}, {"username": "jnunez56", "tweet": "(TX) DONALD TRUMP WON!!!!"}, {"username": "wilchervicki", "tweet": "Trump 2020!"}, {"username": "delsonikekklhl", "tweet": "Go Trump !"}, {"username": "capir5", "tweet": "LONG LIVE PRESIDENT TRUMP."}, {"username": "firstgillespiee", "tweet": "amo a donal trump\ud83d\ude0d\ud83d\ude0d\ud83d\ude0d\ud83d\ude0d"}, {"username": "pbdaileyfl", "tweet": "Typical GOP/Trump crap"}, {"username": "spiritpatti", "tweet": "IFBAP \ud83c\uddfa\ud83c\uddf8TRUMP 2020 \ud83c\uddfa\ud83c\uddf8"}, {"username": "oscar_morris", "tweet": "Sasha Barron Trump"}, {"username": "unimpressedwu", "tweet": "Trump will fire him first"}, {"username": "admphil", "tweet": "Trump won\u203c\ufe0f\ud83c\udfaf\ud83e\udde8\ud83d\udca5\ud83c\uddfa\ud83c\uddf8\ud83c\uddfa\ud83c\uddf8\ud83c\uddfa\ud83c\uddf8\ud83c\uddfa\ud83c\uddf8\ud83c\uddfa\ud83c\uddf8"}, {"username": "eccoscott", "tweet": "Twitter sucks. TRUMP WON"}, {"username": "wandarbts", "tweet": "Health care for all!"}, {"username": "kaigetit", "tweet": "BIDEN \u201cBLUE\u201d MAGA HAT"}, {"username": "jan90067", "tweet": "#Inspiration.  ."}, {"username": "proudofmypotus", "tweet": "#HCQW0RKS"}, {"username": "lacrossemom5", "tweet": "Biden won pidgen"}, {"username": "melvinnudelman", "tweet": "Tell that to Biden"}, {"username": "kanapier1", "tweet": "Biden should pardon her ASAP."}, {"username": "laurie_ishii", "tweet": "Delusional dementia Biden"}, {"username": "caignoredbyedd", "tweet": "Stop McCon."}, {"username": "impatientcatx1", "tweet": "#SaveTheBigCats"}, {"username": "bluesmountain", "tweet": "FBI Forced Biden Investigation"}, {"username": "kelevents", "tweet": "Biden won, bigly."}, {"username": "hubbard2015", "tweet": "That\u2019s when Biden went ahead"}, {"username": "francesnotscott", "tweet": "FAUCI BIDEN HARRIS LETS GO"}, {"username": "duda31087100", "tweet": "EU N\u00c3O T\u00d4 BEM SCRR HAAAAA"}]}