{"sentiment": 60.3, "featured": [{"username": "blest4lif", "tweet": "Trump 2021"}, {"username": "yashiramsp", "tweet": "Mary Trump \ud83d\ude0d"}, {"username": "g_gree9", "tweet": "They just hate trump"}, {"username": "ernestofontan11", "tweet": "More Trump corruption"}, {"username": "lorelei55192275", "tweet": "Arrest Trump Immediately"}, {"username": "mkaffen", "tweet": "Protect trumps victory"}, {"username": "sinzubaba", "tweet": "Trump"}, {"username": "daniloraineri", "tweet": "Grande Trump presidente"}, {"username": "knightking1", "tweet": "#Trump"}, {"username": "frankha74", "tweet": "Trump Crime Family!!"}, {"username": "diana66003861", "tweet": "God Bless President Trump. \ud83d\ude4f\ud83c\udffb"}, {"username": "muskel0ny", "tweet": "this my goat \ud83d\udc10 trump"}, {"username": "coacho1goal", "tweet": "Trumps Garage."}, {"username": "cleo_mio", "tweet": "He is a LOSER!"}, {"username": "mhai56", "tweet": "Yup \ud83d\udc4d"}, {"username": "surprisegold1", "tweet": "\ud83d\udca9\ud83d\udca9\ud83d\udca9\ud83d\udca9\ud83d\udca9 Biden"}, {"username": "oldandstillhere", "tweet": "About time"}, {"username": "biden2049959618", "tweet": "youre just mad you lost lol"}, {"username": "textimama", "tweet": "Biden put weight on it."}, {"username": "soi_2020", "tweet": "Beijing Biden Connection"}, {"username": "lilbarnacles", "tweet": "R\u00e9el"}, {"username": "patriottara", "tweet": "\ud83d\ude4f\ud83c\udffb\ud83d\ude4f\ud83c\udffb\ud83d\ude4f\ud83c\udffb\ud83d\ude4f\ud83c\udffb\ud83d\ude4f\ud83c\udffb"}, {"username": "ir2much4u", "tweet": "Biden is a lunatic ....."}, {"username": "blutexgal", "tweet": "\ud83d\ude02"}, {"username": "sunshineblissxo", "tweet": "Tulsi Gabbard &gt; Joe Biden"}, {"username": "harrietmtubman", "tweet": "THIS"}, {"username": "dagb0t", "tweet": "biden wins?"}, {"username": "americangirl20_", "tweet": "Yeah okay Biden"}, {"username": "paulclaus", "tweet": "Yes.  1000x yes."}, {"username": "blutexgal", "tweet": "\ud83e\udd2c"}, {"username": "wittyduchess", "tweet": "Oh shit"}, {"username": "blutexgal", "tweet": "\ud83e\udd2c"}, {"username": "mhai56", "tweet": "Yes \ud83d\ude4c"}, {"username": "oakborn", "tweet": "Grumble"}, {"username": "blutexgal", "tweet": "\ud83d\ude33"}]}