{"sentiment": 60.8, "featured": [{"username": "watchmewindows", "tweet": "Time's ticking Trump lol"}, {"username": "just_some_dick", "tweet": "Damn this Trump Virus."}, {"username": "star1969", "tweet": "Fight for Trump"}, {"username": "johnny63744939", "tweet": "Trump's result"}, {"username": "alxstep", "tweet": "Trump = Traitor"}, {"username": "maddrenh", "tweet": "Trump university"}, {"username": "elainenorwood5", "tweet": "Just a other hoax per trump.."}, {"username": "anthonyramey5", "tweet": "TRUMP RONA\ud83d\ude0e"}, {"username": "jolo1954", "tweet": "It's the Trump virus!"}, {"username": "bethweb31157322", "tweet": "Love the Trumps!!"}, {"username": "ralphspoilspor4", "tweet": "Trump#1traitor"}, {"username": "elann57", "tweet": "Anti Trump beware!"}, {"username": "gerdmoebehrens", "tweet": "TRUMP WON"}, {"username": "kim_remer", "tweet": "TRUMP 2020!"}, {"username": "btn1100", "tweet": "Trump is so dumb it\u2019s painful."}, {"username": "mslauren2930", "tweet": "Talk about a VERY GOOD THING."}, {"username": "tami32961", "tweet": "#TraitorTrump"}, {"username": "educators4biden", "tweet": "#WhereIsDavidPerdue"}, {"username": "janetgalehubb", "tweet": "Die Biden"}, {"username": "akbashmom", "tweet": "\ud83d\udc47\ud83c\udffc"}, {"username": "poolglitter", "tweet": "Word\ud83c\uddfa\ud83c\uddf8"}, {"username": "mousepadheather", "tweet": "Back later."}, {"username": "stultznancy", "tweet": "Biden Harris won"}, {"username": "caseyresists", "tweet": "Whoever does a better job lol"}, {"username": "kathoover3", "tweet": "Shocking"}, {"username": "deadhead722", "tweet": "#ChickenPurdue"}, {"username": "willtobefree", "tweet": "WOAH"}, {"username": "ukexpat19", "tweet": "The Swamp!"}, {"username": "outpoliticked", "tweet": "WAR!!! #BidenCheated2020"}, {"username": "laura41714925", "tweet": "Biden is a disgrace"}, {"username": "cubsgop", "tweet": "Yes, after Biden concedes"}, {"username": "_dziga_", "tweet": "I fully stan Eli Valley."}, {"username": "butchhall14", "tweet": "Yes Biden need to concead"}, {"username": "antifafreddy", "tweet": "where tf is mario judah?!"}]}