{"sentiment": 55.3, "featured": [{"username": "fightbackmaga", "tweet": "Trump has a 2021 calendar \ud83d\udd25 \ud83d\udd25"}, {"username": "teamtrump_uk", "tweet": "#Trump #Rudy"}, {"username": "angelerickson7", "tweet": "Trump won in a landslide!"}, {"username": "jamiejaco1", "tweet": "Trump won Cali !!"}, {"username": "teamtrump_uk", "tweet": "#Trump #Rudy"}, {"username": "bonafidebait86", "tweet": "These damm Trump supporters"}, {"username": "choctaw_love", "tweet": "YES President Trump!!!!WWGOWGA"}, {"username": "teamtrump_uk", "tweet": "#Trump #Rudy"}, {"username": "teamtrump_uk", "tweet": "#Trump  #Rudy"}, {"username": "jam1159", "tweet": "But he \"Loves Trump \"."}, {"username": "witness2a", "tweet": "These are trump\u2019s great people"}, {"username": "unmaskedmindset", "tweet": "Biden\u2019s America"}, {"username": "jillmaleson", "tweet": "#DiaperDon"}, {"username": "trackerem", "tweet": "Biden. With his broken ankle."}, {"username": "stonest93969905", "tweet": "Biden from Quebec journal"}, {"username": "txvoodoo", "tweet": "Is there a google outage?"}, {"username": "onetrueray", "tweet": "this but unironically"}, {"username": "sagouspemary", "tweet": "Biden\u2019s World.."}]}