{"sentiment": 56.4, "featured": [{"username": "candygirlclw", "tweet": "President Trump won!"}, {"username": "dougsullivant", "tweet": "DONALD TRUMP WON!"}, {"username": "trumpsaysthis", "tweet": "Trump says this"}, {"username": "sharp8lottie", "tweet": "Trump just keeps loosing."}, {"username": "leona05819610", "tweet": "If it's what Trump recommends"}, {"username": "daub14b", "tweet": "Trump won #All50States!"}, {"username": "pcon1", "tweet": "#Trump\u2019sAmerica"}, {"username": "yarafilms", "tweet": "Donald Trump Won the Election"}, {"username": "anthonybuckla20", "tweet": "Trump incited him to kill."}, {"username": "gregariousbiped", "tweet": "Trump is my enemy."}, {"username": "1978fastback", "tweet": "Trump won Georgia."}, {"username": "eyeswid28556330", "tweet": "Trump +4!!!"}, {"username": "geesebumps_pod", "tweet": "She's Trump's coke dealer"}, {"username": "quintal_rich", "tweet": "Trump won"}, {"username": "adraeng", "tweet": "GO TRUMP"}, {"username": "elroy2_mc", "tweet": "TRUMP 2020!\ud83c\uddfa\ud83c\uddf8"}, {"username": "judyblue51", "tweet": "Trump  2020"}, {"username": "stuckwfineline", "tweet": "shading trump? I LOVE IT HERE"}, {"username": "tiredoftrump8", "tweet": "Biden: 81,264,673"}, {"username": "kaydlane22", "tweet": "\ud83d\udc4f\ud83d\udc4f\ud83d\udc4f\ud83d\udc4f"}, {"username": "teresag41219764", "tweet": "Biden is nuts"}, {"username": "marv3lxstill", "tweet": "HES SO BEAUTIFUL TOO??"}, {"username": "brandonpohja", "tweet": "\ud83e\udd14 Biden is a placeholder."}, {"username": "brittanylovesc", "tweet": "Come on Biden!!! \ud83d\ude29\ud83d\ude29\ud83d\ude4c\ud83c\udffe\ud83d\ude4c\ud83c\udffe"}, {"username": "dewayne7466", "tweet": "Biden can fuck himself."}, {"username": "walters429b", "tweet": "This\u2b07\ufe0f\u2b07\ufe0f"}, {"username": "tiredoftrump8", "tweet": "Biden: 81,264,673"}, {"username": "bidenbidenbiden", "tweet": "#trumpVirus\ud83e\udda0 #BidenVaccine\ud83d\udc89"}, {"username": "jahosiphats", "tweet": "This is the future of the DNC"}, {"username": "ezraorwhatever", "tweet": "Thank you joe Biden"}, {"username": "tiredoftrump8", "tweet": "Biden: 81,264,673"}, {"username": "eddiem888", "tweet": "Yes Zir"}, {"username": "capitulatebiden", "tweet": "No dispute here, Twitter"}, {"username": "rsprag1", "tweet": "Biden look awesome!"}, {"username": "canonbabe1", "tweet": "Hint: Biden - Oppose - yes."}, {"username": "tiredoftrump8", "tweet": "Biden: 81,264,673"}, {"username": "h8usernames", "tweet": "Sounds about right..."}, {"username": "mvpsimmons", "tweet": "Comrade Biden"}, {"username": "1978fastback", "tweet": "Biden cheated and still lost."}, {"username": "divalicioussas", "tweet": "Disgraceful"}, {"username": "milocooper14", "tweet": "Joe Biden is no one to me."}]}