{"sentiment": 58.4, "featured": [{"username": "s_tpwk", "tweet": "trump"}, {"username": "yourlilaa", "tweet": "orange trump....."}, {"username": "kimbowe13123683", "tweet": "We Love you President Trump."}, {"username": "rickrick041560", "tweet": "This is what trump has caused"}, {"username": "billreno4", "tweet": "trumps gestapo"}, {"username": "johnwel63452747", "tweet": "Criminal Trump family"}, {"username": "lessfortunate7", "tweet": "Let it go trump u lost"}, {"username": "brigitt88466318", "tweet": "Trump schafft es!!"}, {"username": "goldenphoto_pro", "tweet": "#Bolsanaro Trumps Man."}, {"username": "yaniikasimpasa", "tweet": "o sanarsin donald trump"}, {"username": "badov49", "tweet": "Trump Victory Rally"}, {"username": "karen92607762", "tweet": "Trump already won!!!"}, {"username": "suejoyvt", "tweet": "I'm still with Trump!"}, {"username": "spponhadle1970", "tweet": "Trump won YUGE"}, {"username": "badov49", "tweet": "Trump rally Saturday"}, {"username": "kinghorsewrites", "tweet": "The Trump modus operandi..."}, {"username": "tac80349840", "tweet": "DONALD TRUMP WON"}, {"username": "tribble_bait", "tweet": "Listen to Rush.  He\u2019s \ud83d\udd25"}, {"username": "ridlonsa", "tweet": "We did  - we elected Joe Biden"}, {"username": "hops68", "tweet": "\ud83e\udd23\ud83e\udd23\ud83e\udd23"}, {"username": "kublaiyan", "tweet": "Big Mouth is fucking genius"}, {"username": "beltdusti", "tweet": "#SuitCaseGate Biden cheated"}, {"username": "lsmontoya", "tweet": "#RudyFreeman #ShayeShayeMoss"}, {"username": "s_tpwk", "tweet": "biden"}, {"username": "yourlilaa", "tweet": "biden"}, {"username": "wade_turnbull", "tweet": "More blueMAGA"}, {"username": "lizusa4life", "tweet": "Biden into bestiality"}, {"username": "ferman_nenas", "tweet": "Almanya'n\u0131n umudu Biden"}, {"username": "twostarrz72", "tweet": "Facts"}, {"username": "sonyatish", "tweet": "Biden shows his true colors."}, {"username": "bbyhazlouu", "tweet": "biden"}, {"username": "asensiotw", "tweet": "* ponen foto de Biden *"}, {"username": "jshep717", "tweet": "biden is a joke"}, {"username": "harrysv0id", "tweet": "king biden"}, {"username": "willwilberforc4", "tweet": "VP Biden!"}, {"username": "kianstaylor", "tweet": "Joe Biden"}, {"username": "clayjrstaves", "tweet": "Biden hurt the most."}, {"username": "hillaryzmyhmgrl", "tweet": "I've loved her all my life."}, {"username": "canucks4trump1", "tweet": ".... fuck joe Biden ..."}, {"username": "egodeath666_", "tweet": "biden\u2019s america\ud83d\ude10"}, {"username": "sandman0011", "tweet": "VP Biden lost:)"}]}